{"height":135,"infinite":false,"layers":[{"draworder":"topdown","id":8,"name":"grid","objects":[{"height":0,"id":6,"name":"","polygon":[{"x":0,"y":8},{"x":1920,"y":-1072},{"x":1920,"y":8},{"x":0,"y":-1072}],"rotation":0,"type":"","visible":true,"width":0,"x":0,"y":1072},{"height":0,"id":7,"name":"","polygon":[{"x":0,"y":0},{"x":0,"y":-544},{"x":0,"y":-1080},{"x":960,"y":-544},{"x":-960,"y":-544}],"rotation":0,"type":"","visible":true,"width":0,"x":960,"y":1080}],"opacity":1,"type":"objectgroup","visible":true,"x":0,"y":0},{"draworder":"topdown","id":11,"name":"trianglepath","objects":[{"height":0,"id":525,"name":"trianglepath","polygon":[{"x":0,"y":0},{"x":768,"y":0},{"x":384,"y":64}],"rotation":0,"type":"","visible":true,"width":0,"x":80,"y":984},{"height":0,"id":584,"name":"trianglepath","polygon":[{"x":0,"y":0},{"x":608,"y":0},{"x":304,"y":64}],"rotation":0,"type":"","visible":true,"width":0,"x":16,"y":200},{"height":0,"id":613,"name":"trianglepath","polygon":[{"x":0,"y":0},{"x":832,"y":0},{"x":416,"y":64}],"rotation":0,"type":"","visible":true,"width":0,"x":992,"y":984},{"height":0,"id":615,"name":"trianglepath","polygon":[{"x":0,"y":0},{"x":832,"y":0},{"x":416,"y":64}],"rotation":0,"type":"","visible":true,"width":0,"x":992,"y":984},{"height":0,"id":621,"name":"trianglepath","polygon":[{"x":0,"y":0},{"x":592,"y":0},{"x":296,"y":64}],"rotation":0,"type":"","visible":true,"width":0,"x":1064,"y":200},{"height":0,"id":628,"name":"trianglepath","polygon":[{"x":0,"y":0},{"x":768,"y":0},{"x":384,"y":64}],"rotation":0,"type":"","visible":true,"width":0,"x":80,"y":984}],"opacity":1,"type":"objectgroup","visible":true,"x":0,"y":0},{"draworder":"topdown","id":5,"name":"exit","objects":[{"height":64,"id":589,"name":"exit","rotation":0,"type":"","visible":true,"width":64,"x":928,"y":72}],"opacity":1,"type":"objectgroup","visible":true,"x":0,"y":0},{"draworder":"topdown","id":3,"name":"platform","objects":[{"height":944,"id":510,"name":"platform","rotation":0,"type":"","visible":true,"width":64,"x":928,"y":136},{"height":32,"id":521,"name":"platform","rotation":0,"type":"","visible":true,"width":680,"x":1064,"y":264},{"height":32,"id":524,"name":"platform","rotation":0,"type":"","visible":true,"width":1920,"x":0,"y":1048},{"height":32,"id":548,"name":"platform","rotation":0,"type":"","visible":true,"width":96,"x":896,"y":792},{"height":32,"id":549,"name":"platform","rotation":0,"type":"","visible":true,"width":24,"x":752,"y":792},{"height":32,"id":550,"name":"platform","rotation":0,"type":"","visible":true,"width":24,"x":608,"y":792},{"height":32,"id":551,"name":"platform","rotation":0,"type":"","visible":true,"width":24,"x":320,"y":792},{"height":32,"id":552,"name":"platform","rotation":0,"type":"","visible":true,"width":24,"x":464,"y":792},{"height":32,"id":554,"name":"platform","rotation":0,"type":"","visible":true,"width":24,"x":112,"y":632},{"height":32,"id":562,"name":"platform","rotation":0,"type":"","visible":true,"width":24,"x":616,"y":552},{"height":32,"id":563,"name":"platform","rotation":0,"type":"","visible":true,"width":24,"x":472,"y":552},{"height":32,"id":564,"name":"platform","rotation":0,"type":"","visible":true,"width":24,"x":328,"y":552},{"height":32,"id":566,"name":"platform","rotation":0,"type":"","visible":true,"width":24,"x":760,"y":552},{"height":32,"id":568,"name":"platform","rotation":0,"type":"","visible":true,"width":24,"x":176,"y":792},{"height":32,"id":569,"name":"platform","rotation":0,"type":"","visible":true,"width":24,"x":184,"y":552},{"height":32,"id":581,"name":"platform","rotation":0,"type":"","visible":true,"width":96,"x":896,"y":264},{"height":32,"id":582,"name":"platform","rotation":0,"type":"","visible":true,"width":704,"x":0,"y":264},{"height":1080,"id":583,"name":"platform","rotation":0,"type":"","visible":true,"width":16,"x":0,"y":0},{"height":16,"id":587,"name":"platform","rotation":0,"type":"","visible":true,"width":1920,"x":0,"y":0},{"height":1072,"id":591,"name":"platform","rotation":0,"type":"","visible":true,"width":16,"x":1904,"y":8},{"height":32,"id":601,"name":"platform","rotation":0,"type":"","visible":true,"width":24,"x":1152,"y":792},{"height":32,"id":602,"name":"platform","rotation":0,"type":"","visible":true,"width":24,"x":1440,"y":792},{"height":32,"id":603,"name":"platform","rotation":0,"type":"","visible":true,"width":24,"x":1296,"y":792},{"height":32,"id":604,"name":"platform","rotation":0,"type":"","visible":true,"width":24,"x":1584,"y":792},{"height":32,"id":605,"name":"platform","rotation":0,"type":"","visible":true,"width":24,"x":1728,"y":792},{"height":32,"id":606,"name":"platform","rotation":0,"type":"","visible":true,"width":96,"x":1872,"y":792},{"height":32,"id":607,"name":"platform","rotation":0,"type":"","visible":true,"width":24,"x":1088,"y":632},{"height":32,"id":608,"name":"platform","rotation":0,"type":"","visible":true,"width":24,"x":1160,"y":552},{"height":32,"id":609,"name":"platform","rotation":0,"type":"","visible":true,"width":24,"x":1736,"y":552},{"height":32,"id":610,"name":"platform","rotation":0,"type":"","visible":true,"width":24,"x":1304,"y":552},{"height":32,"id":611,"name":"platform","rotation":0,"type":"","visible":true,"width":24,"x":1448,"y":552},{"height":32,"id":612,"name":"platform","rotation":0,"type":"","visible":true,"width":24,"x":1592,"y":552},{"height":32,"id":618,"name":"platform","rotation":0,"type":"","visible":true,"width":128,"x":864,"y":520},{"height":32,"id":619,"name":"platform","rotation":0,"type":"","visible":true,"width":128,"x":1840,"y":520},{"height":32,"id":620,"name":"platform","rotation":0,"type":"","visible":true,"width":96,"x":1872,"y":264},{"height":32,"id":626,"name":"platform","rotation":0,"type":"","visible":true,"width":64,"x":16,"y":936}],"opacity":1,"type":"objectgroup","visible":true,"x":0,"y":0},{"draworder":"topdown","id":13,"name":"polygon","objects":[{"height":0,"id":543,"name":"polygon","polygon":[{"x":0,"y":0},{"x":0,"y":-40},{"x":28,"y":-64},{"x":56,"y":-40},{"x":56,"y":0}],"rotation":0,"type":"","visible":true,"width":0,"x":452,"y":1048},{"height":0,"id":585,"name":"polygon","polygon":[{"x":0,"y":0},{"x":0,"y":-40},{"x":28,"y":-64},{"x":56,"y":-40},{"x":56,"y":0}],"rotation":0,"type":"","visible":true,"width":0,"x":364,"y":264},{"height":0,"id":624,"name":"polygon","polygon":[{"x":0,"y":0},{"x":0,"y":-40},{"x":28,"y":-64},{"x":56,"y":-40},{"x":56,"y":0}],"rotation":0,"type":"","visible":true,"width":0,"x":1376,"y":264}],"opacity":1,"type":"objectgroup","visible":true,"x":0,"y":0},{"draworder":"topdown","id":2,"name":"player","objects":[{"ellipse":true,"height":48,"id":481,"name":"player","rotation":0,"type":"","visible":true,"width":48,"x":24,"y":888}],"opacity":1,"type":"objectgroup","visible":true,"x":0,"y":0},{"draworder":"topdown","id":6,"name":"square","objects":[{"height":48,"id":436,"name":"square","rotation":0,"type":"","visible":true,"width":48,"x":1008,"y":1000},{"height":48,"id":486,"name":"square","rotation":0,"type":"","visible":true,"width":48,"x":864,"y":1000},{"height":48,"id":520,"name":"square","rotation":0,"type":"","visible":true,"width":48,"x":1600,"y":216},{"height":48,"id":560,"name":"square","rotation":0,"type":"","visible":true,"width":48,"x":864,"y":472},{"height":48,"id":586,"name":"square","rotation":0,"type":"","visible":true,"width":48,"x":32,"y":216},{"height":48,"id":588,"name":"square","rotation":0,"type":"","visible":true,"width":48,"x":656,"y":216},{"height":48,"id":600,"name":"square","rotation":0,"type":"","visible":true,"width":48,"x":1840,"y":1000},{"height":48,"id":617,"name":"square","rotation":0,"type":"","visible":true,"width":48,"x":1840,"y":472},{"height":48,"id":623,"name":"square","rotation":0,"type":"","visible":true,"width":48,"x":1160,"y":216}],"opacity":1,"type":"objectgroup","visible":true,"x":0,"y":0},{"draworder":"topdown","id":7,"name":"bounce","objects":[{"height":32,"id":590,"name":"bounce","rotation":0,"type":"","visible":true,"width":32,"x":784,"y":264}],"opacity":1,"type":"objectgroup","visible":true,"x":0,"y":0},{"draworder":"topdown","id":9,"name":"spike","objects":[{"height":0,"id":546,"name":"spike","polygon":[{"x":0,"y":0},{"x":16,"y":16},{"x":128,"y":16},{"x":128,"y":0},{"x":120,"y":-8},{"x":112,"y":0},{"x":104,"y":-8},{"x":96,"y":0},{"x":88,"y":-8},{"x":80,"y":0},{"x":72,"y":-8},{"x":64,"y":0},{"x":56,"y":-8},{"x":48,"y":0},{"x":40,"y":-8},{"x":32,"y":0},{"x":24,"y":-8},{"x":16,"y":0},{"x":8,"y":-8}],"rotation":0,"type":"","visible":true,"width":0,"x":864,"y":1048},{"height":0,"id":558,"name":"spike","polygon":[{"x":0,"y":0},{"x":16,"y":16},{"x":128,"y":16},{"x":128,"y":0},{"x":120,"y":-8},{"x":112,"y":0},{"x":104,"y":-8},{"x":96,"y":0},{"x":88,"y":-8},{"x":80,"y":0},{"x":72,"y":-8},{"x":64,"y":0},{"x":56,"y":-8},{"x":48,"y":0},{"x":40,"y":-8},{"x":32,"y":0},{"x":24,"y":-8},{"x":16,"y":0},{"x":8,"y":-8}],"rotation":0,"type":"","visible":true,"width":0,"x":864,"y":520},{"height":0,"id":616,"name":"spike","polygon":[{"x":0,"y":0},{"x":16,"y":16},{"x":128,"y":16},{"x":128,"y":0},{"x":120,"y":-8},{"x":112,"y":0},{"x":104,"y":-8},{"x":96,"y":0},{"x":88,"y":-8},{"x":80,"y":0},{"x":72,"y":-8},{"x":64,"y":0},{"x":56,"y":-8},{"x":48,"y":0},{"x":40,"y":-8},{"x":32,"y":0},{"x":24,"y":-8},{"x":16,"y":0},{"x":8,"y":-8}],"rotation":0,"type":"","visible":true,"width":0,"x":1840,"y":520},{"height":0,"id":625,"name":"spike","polygon":[{"x":0,"y":0},{"x":16,"y":16},{"x":112,"y":16},{"x":128,"y":0},{"x":120,"y":-8},{"x":112,"y":0},{"x":104,"y":-8},{"x":96,"y":0},{"x":88,"y":-8},{"x":80,"y":0},{"x":72,"y":-8},{"x":64,"y":0},{"x":56,"y":-8},{"x":48,"y":0},{"x":40,"y":-8},{"x":32,"y":0},{"x":24,"y":-8},{"x":16,"y":0},{"x":8,"y":-8}],"rotation":0,"type":"","visible":true,"width":0,"x":928,"y":1048}],"opacity":1,"type":"objectgroup","visible":true,"x":0,"y":0}],"nextlayerid":16,"nextobjectid":629,"orientation":"orthogonal","renderorder":"right-down","tiledversion":"1.2.3","tileheight":8,"tilesets":[],"tilewidth":8,"type":"map","version":1.2,"width":240}